ranorex_report_parser/__init__.py
ranorex_report_parser/parser.py
ranorex_report_parser/elements/__init__.py
ranorex_report_parser/elements/base.py
ranorex_report_parser/elements/config_elements.py
ranorex_report_parser/elements/item.py
ranorex_report_parser/elements/iteration_container.py
ranorex_report_parser/elements/module_group.py
ranorex_report_parser/elements/report.py
ranorex_report_parser/elements/smart_folder.py
ranorex_report_parser/elements/test_case.py
ranorex_report_parser/elements/test_module.py
ranorex_report_parser/elements/test_suite.py
ranorex_report_parser-0.1.9.dist-info/METADATA
ranorex_report_parser-0.1.9.dist-info/WHEEL
ranorex_report_parser-0.1.9.dist-info/top_level.txt
ranorex_report_parser-0.1.9.dist-info/RECORD
